slice/__init__.py
slice/__main__.py
slice/fontresources.py
slice/imageresources.py
slice/instanceworker.py
slice/models.py
slice/ui/__init__.py
slice/ui/dialogs.py
slice/ui/widgets.py
slicegui-0.7.1.dist-info/LICENSE
slicegui-0.7.1.dist-info/METADATA
slicegui-0.7.1.dist-info/WHEEL
slicegui-0.7.1.dist-info/entry_points.txt
slicegui-0.7.1.dist-info/top_level.txt
slicegui-0.7.1.dist-info/RECORD
