Metadata-Version: 2.1
Name: slicegui
Version: 0.7.1
Summary: An open-source GUI application to create custom font design spaces from variable fonts
Home-page: https://github.com/source-foundry/Slice
Author: Source Foundry Authors
Author-email: chris@sourcefoundry.org
License: GNU General Public License v3 (GPLv3)
Platform: Any
Classifier: Development Status :: 4 - Beta
Classifier: Intended Audience :: Developers
Classifier: Intended Audience :: End Users/Desktop
Classifier: License :: OSI Approved :: GNU General Public License v3 (GPLv3)
Classifier: Natural Language :: English
Classifier: Operating System :: OS Independent
Classifier: Programming Language :: Python
Classifier: Programming Language :: Python :: 3
Classifier: Programming Language :: Python :: 3.6
Classifier: Programming Language :: Python :: 3.7
Classifier: Programming Language :: Python :: 3.8
Classifier: Programming Language :: Python :: 3.9
Classifier: Topic :: Multimedia
Requires-Python: >=3.6.0
Requires-Dist: fontTools (>=4.21.1)
Provides-Extra: dev
Requires-Dist: coverage ; extra == 'dev'
Requires-Dist: pytest ; extra == 'dev'
Requires-Dist: pytest-qt ; extra == 'dev'
Requires-Dist: tox ; extra == 'dev'
Requires-Dist: flake8 ; extra == 'dev'
Requires-Dist: black ; extra == 'dev'
Requires-Dist: isort ; extra == 'dev'
Provides-Extra: maintain
Requires-Dist: wheel ; extra == 'maintain'
Requires-Dist: setuptools ; extra == 'maintain'
Requires-Dist: twine ; extra == 'maintain'
